morty/__init__.py
morty/__main__.py
morty/cli/__init__.py
morty/cli/commands.py
morty/common/__init__.py
morty/common/filesystem.py
morty/common/formats.py
morty/common/serialize.py
morty/config/__init__.py
morty/config/loaders.py
morty/config/registries.py
morty/dashboard/__init__.py
morty/dashboard/backend/__init__.py
morty/dashboard/indexers.py
morty/dashboard/summarizers.py
morty/exceptions.py
morty/experiments.py
morty/logger.py
morty/managers.py
morty/reproduce.py
morty/trackers/__init__.py
morty/trackers/base.py
morty/trackers/git.py
morty/trackers/stdout.py
morty/trackers/traceback.py
morty/trainers/__init__.py
morty/trainers/pytorch.py
morty/trainers/sklearn.py
morty/trainers/tensorflow.py
morty/utils/__init__.py
morty/utils/integrations.py
morty-0.3.0.dist-info/entry_points.txt
morty-0.3.0.dist-info/WHEEL
morty-0.3.0.dist-info/METADATA
morty-0.3.0.dist-info/RECORD
