Metadata-Version: 2.1
Name: morty
Version: 0.3.0
Summary: TBU
Home-page: https://github.com/roma-glushko/morty
License: MIT
Keywords: machine-learning,experiment-tracking,deep-learning
Author: Roman Glushko
Author-email: roman.glushko.m@gmail.com
Requires-Python: >=3.7,<4.0
Classifier: License :: OSI Approved :: MIT License
Classifier: Programming Language :: Python :: 3
Classifier: Programming Language :: Python :: 3.10
Classifier: Programming Language :: Python :: 3.7
Classifier: Programming Language :: Python :: 3.8
Classifier: Programming Language :: Python :: 3.9
Provides-Extra: tensorflow
Provides-Extra: tf
Requires-Dist: Flask (>=2.0.2,<3.0.0)
Requires-Dist: click (>=8.0.1,<9.0.0)
Requires-Dist: funkybob (>=2018.5.1,<2019.0.0)
Requires-Dist: humanfriendly (>=10.0,<11.0)
Requires-Dist: rich (>=10.11.0,<11.0.0)
Requires-Dist: tabulate (>=0.8.9,<0.9.0)
Requires-Dist: tensorflow (>=2.6.0,<3.0.0); extra == "tf" or extra == "tensorflow"
Requires-Dist: typer (>=0.4.0,<0.5.0)
Project-URL: Bug Tracker, https://github.com/roma-glushko/morty/issues
Project-URL: Repository, https://github.com/roma-glushko/morty.git
